llm_to_mcp_integration_engine/__init__.py
llm_to_mcp_integration_engine/__main__.py
llm_to_mcp_integration_engine/config.py
llm_to_mcp_integration_engine/cot_verifier.py
llm_to_mcp_integration_engine/exceptions.py
llm_to_mcp_integration_engine/executor.py
llm_to_mcp_integration_engine/finder.py
llm_to_mcp_integration_engine/integrator.py
llm_to_mcp_integration_engine/llm_to_mcp_integration_engine.py
llm_to_mcp_integration_engine/logging.py
llm_to_mcp_integration_engine/registry.py
llm_to_mcp_integration_engine/retry.py
llm_to_mcp_integration_engine/retry_strategies.py
llm_to_mcp_integration_engine/schema.py
llm_to_mcp_integration_engine/utils.py
llm_to_mcp_integration_engine/validators.py
llm_to_mcp_integration_engine/core/executor.py
llm_to_mcp_integration_engine/core/integrator.py
llm_to_mcp_integration_engine/core/json_handler.py
llm_to_mcp_integration_engine/core/non_json_handler.py
llm_to_mcp_integration_engine/core/tool_interface.py
llm_to_mcp_integration_engine-0.1.0.dist-info/licenses/AUTHORS.rst
llm_to_mcp_integration_engine-0.1.0.dist-info/METADATA
llm_to_mcp_integration_engine-0.1.0.dist-info/WHEEL
llm_to_mcp_integration_engine-0.1.0.dist-info/top_level.txt
llm_to_mcp_integration_engine-0.1.0.dist-info/RECORD
