Metadata-Version: 2.4
Name: llm_to_mcp_integration_engine
Version: 0.1.0
Summary: A robust integration engine that enhances communication between LLMs and MCP servers/functions with validation, retries, and safety.
Author-email: Michael Alamin <michaelalamin9@gmail.com>
Maintainer-email: Michael Alamin <michaelalamin9@gmail.com>
License: Not open source
Project-URL: homepage, https://github.com/Million19/llm_to_mcp_integration_engine
Project-URL: bugs, https://github.com/Million19/llm_to_mcp_integration_engine/issues
Project-URL: changelog, https://github.com/Million19/llm_to_mcp_integration_engine/blob/master/changelog.md
Classifier: Development Status :: 4 - Beta
Classifier: Intended Audience :: Developers
Classifier: License :: Other/Proprietary License
Classifier: Programming Language :: Python
Classifier: Programming Language :: Python :: 3
Classifier: Programming Language :: Python :: 3.8
Classifier: Programming Language :: Python :: 3.9
Classifier: Programming Language :: Python :: 3.10
Classifier: Operating System :: OS Independent
Classifier: Topic :: Software Development :: Libraries
Classifier: Topic :: Software Development :: User Interfaces
Classifier: Typing :: Typed
License-File: AUTHORS.rst
Requires-Dist: typer>=0.9
Requires-Dist: rich>=13.0.0
Provides-Extra: dev
Requires-Dist: coverage; extra == "dev"
Requires-Dist: pytest; extra == "dev"
Requires-Dist: mypy; extra == "dev"
Requires-Dist: ruff; extra == "dev"
Requires-Dist: build; extra == "dev"
Requires-Dist: twine; extra == "dev"
Dynamic: license-file
